gitvaultscanner/__init__.py
gitvaultscanner/cli.py
gitvaultscanner-1.0.0.dist-info/licenses/LICENSE
gitvaultscanner-1.0.0.dist-info/METADATA
gitvaultscanner-1.0.0.dist-info/WHEEL
gitvaultscanner-1.0.0.dist-info/entry_points.txt
gitvaultscanner-1.0.0.dist-info/top_level.txt
gitvaultscanner-1.0.0.dist-info/RECORD
