Metadata-Version: 2.4
Name: gitvaultscanner
Version: 1.0.0
Summary: Advanced secrets scanner for GitHub repositories and local directories
Home-page: https://github.com/yourusername/GitVaultScanner
Author: AlexandrGonin
Author-email: alexandrgonin000@gmal.com
Project-URL: Bug Tracker, https://github.com/yourusername/GitVaultScanner/issues
Project-URL: Source Code, https://github.com/yourusername/GitVaultScanner
Keywords: security,scanner,secrets,github,security-audit,devsecops
Classifier: Programming Language :: Python :: 3
Classifier: Programming Language :: Python :: 3.7
Classifier: Programming Language :: Python :: 3.8
Classifier: Programming Language :: Python :: 3.9
Classifier: Programming Language :: Python :: 3.10
Classifier: Programming Language :: Python :: 3.11
Classifier: License :: OSI Approved :: MIT License
Classifier: Operating System :: OS Independent
Classifier: Development Status :: 4 - Beta
Classifier: Intended Audience :: Developers
Classifier: Topic :: Security
Classifier: Topic :: Software Development :: Quality Assurance
Requires-Python: >=3.7
License-File: LICENSE
Requires-Dist: requests>=2.28.0
Requires-Dist: colorama>=0.4.6
Dynamic: author
Dynamic: author-email
Dynamic: classifier
Dynamic: description
Dynamic: description-content-type
Dynamic: home-page
Dynamic: keywords
Dynamic: license-file
Dynamic: project-url
Dynamic: requires-dist
Dynamic: requires-python
Dynamic: summary
